detvista_airflow/__init__.py
detvista_airflow/operators/__init__.py
detvista_airflow/operators/common/CsvToRDBOperator.py
detvista_airflow/operators/common/RDBSqlExecutionOperator.py
detvista_airflow/operators/common/RDBToCsvOperator.py
detvista_airflow/operators/common/RDBToRDBOperator.py
detvista_airflow/operators/common/VariableOperator.py
detvista_airflow/operators/common/__init__.py
detvista_airflow/operators/mysql/CsvToMysqlOperator.py
detvista_airflow/operators/mysql/MysqlSqlExecutionOperator.py
detvista_airflow/operators/mysql/MysqlToCsvOperator.py
detvista_airflow/operators/mysql/MysqlToMysqlOperator.py
detvista_airflow/operators/mysql/__init__.py
detvista_airflow/operators/oracle/CsvToOracleOperator.py
detvista_airflow/operators/oracle/OracleToCsvOperator.py
detvista_airflow/operators/oracle/__init__.py
detvista_airflow/operators/postgres/CsvToPostgresOperator.py
detvista_airflow/operators/postgres/PostgresSqlExecutionOperator.py
detvista_airflow/operators/postgres/PostgresToCsvOperator.py
detvista_airflow/operators/postgres/PostgresToPostgresOperator.py
detvista_airflow/operators/postgres/__init__.py
detvista_airflow_common-1.1.2.dist-info/METADATA
detvista_airflow_common-1.1.2.dist-info/WHEEL
detvista_airflow_common-1.1.2.dist-info/top_level.txt
detvista_airflow_common-1.1.2.dist-info/RECORD
